relation_graph-0.1.1.dist-info/METADATA
relation_graph-0.1.1.dist-info/WHEEL
relation_graph-0.1.1.dist-info/entry_points.txt
relation_graph_impl/__init__.py
relation_graph_impl/relation_graph_impl.cpython-37m-x86_64-linux-gnu.so
relation_graph-0.1.1.dist-info/RECORD
